{
  "identificacion" : {
    "version" : 3,
    "ambiente" : "01",
    "tipoDte" : "03",
    "numeroControl" : "DTE-03-00120012-000000000138787",
    "codigoGeneracion" : "8DEC3B7E-B1E5-4296-9274-C59E8F355A3F",
    "tipoModelo" : 1,
    "tipoOperacion" : 1,
    "tipoContingencia" : null,
    "motivoContin" : null,
    "fecEmi" : "2024-09-20",
    "horEmi" : "08:54:14",
    "tipoMoneda" : "USD"
  },
  "documentoRelacionado" : null,
  "emisor" : {
    "nit" : "06143006630016",
    "nrc" : "5460",
    "nombre" : "INDUSTRIAS CONSOLIDADAS, LTDA. DE C.V. ",
    "codActividad" : "23101",
    "descActividad" : "Fabricación de vidrio",
    "nombreComercial" : "INCO,  LTDA. DE C.V.",
    "tipoEstablecimiento" : "01",
    "direccion" : {
      "departamento" : "06",
      "municipio" : "02",
      "complemento" : "Carretera Troncal del Norte,  Kilometro 12 1/2 ,Barrio San Sebastian, Apopa"
    },
    "telefono" : "22076183",
    "correo" : "apopa@inco.com.sv",
    "codEstableMH" : null,
    "codEstable" : "0012",
    "codPuntoVentaMH" : null,
    "codPuntoVenta" : "0012"
  },
  "receptor" : {
    "nit" : "06041312600010",
    "nrc" : "2569332",
    "nombre" : "LOPEZ GOMEZ, NATANAEL",
    "codActividad" : "46633",
    "descActividad" : "Vidrierías",
    "nombreComercial" : null,
    "direccion" : {
      "departamento" : "06",
      "municipio" : "02",
      "complemento" : "10 CALLE ORIENTE, #224-A, SAN SALVADOR, SAN SALVADOR, SAN SALVADOR"
    },
    "telefono" : "503   -7711-9355           ",
    "correo" : "lopezgomeznatanael@gmail.com"
  },
  "otrosDocumentos" : null,
  "ventaTercero" : null,
  "cuerpoDocumento" : [ {
    "numItem" : 1,
    "tipoItem" : 1,
    "numeroDocumento" : null,
    "codigo" : "11073001",
    "codTributo" : null,
    "descripcion" : "VIDRIO BRONCE 5MM FLOTADO",
    "cantidad" : 20,
    "uniMedida" : 59,
    "precioUni" : 35.398,
    "montoDescu" : 0,
    "ventaNoSuj" : 0,
    "ventaExenta" : 0,
    "ventaGravada" : 707.96,
    "tributos" : [ "20" ],
    "psv" : 0,
    "noGravado" : 0
  } ],
  "resumen" : {
    "totalNoSuj" : 0,
    "totalExenta" : 0,
    "totalGravada" : 707.96,
    "subTotalVentas" : 707.96,
    "descuNoSuj" : 0,
    "descuExenta" : 0,
    "descuGravada" : 0,
    "porcentajeDescuento" : 0,
    "totalDescu" : 0,
    "tributos" : [ {
      "codigo" : "20",
      "descripcion" : "Impuesto al Valor Agregado 13%",
      "valor" : 92.03
    } ],
    "subTotal" : 707.96,
    "ivaPerci1" : 7.08,
    "ivaRete1" : 0,
    "reteRenta" : 0,
    "montoTotalOperacion" : 799.99,
    "totalNoGravado" : 0,
    "totalPagar" : 807.07,
    "totalLetras" : "OCHOCIENTOS SIETE  07/100 DOLARES",
    "saldoFavor" : 0,
    "condicionOperacion" : 1,
    "pagos" : [ {
      "codigo" : "05",
      "montoPago" : 807.07,
      "referencia" : null,
      "periodo" : null,
      "plazo" : null
    } ],
    "numPagoElectronico" : "0"
  },
  "extension" : {
    "nombEntrega" : "WILFREDO ANTONIO MEJIA DE PAZ           ",
    "docuEntrega" : "05167099-7          ",
    "nombRecibe" : null,
    "docuRecibe" : null,
    "observaciones" : null,
    "placaVehiculo" : null
  },
  "apendice" : null,
  "selloRecepcion" : "2024CB13418D5E22464C96B91891CCF48DBAHRUM"
}